Metadata-Version: 2.1
Name: patron_bernardo_gafas
Version: 0.1
Summary: Es una funcion devuelve un patron con formato de gafas teniendo en cuenta un numero y un nombre
Home-page: https://github.com/Bernardo2502/BernardoPaquete
Author: Bernardo Moreno
Author-email: bernardomorenocacheado2502@gmail.com
